den/VERSION
den/__init__.py
den/__main__.py
den/propane.py
den/thermostat.py
den/weather.py
den-1.3.0.dist-info/DESCRIPTION.rst
den-1.3.0.dist-info/METADATA
den-1.3.0.dist-info/RECORD
den-1.3.0.dist-info/WHEEL
den-1.3.0.dist-info/entry_points.txt
den-1.3.0.dist-info/metadata.json
den-1.3.0.dist-info/top_level.txt
