Metadata-Version: 2.0
Name: den
Version: 1.3.0
Summary: Den is a home for your home's data.
Home-page: https://git.io/k20e
Author: Kris Molendyke
Author-email: kris@k20e.com
License: MIT
Keywords: nest thermostat smoke alarm camera weather propane monitor
Platform: UNKNOWN
Classifier: Development Status :: 3 - Alpha
Classifier: Intended Audience :: Developers
Classifier: Programming Language :: Python :: 2.7
Classifier: Programming Language :: Python :: 3.5
Classifier: Programming Language :: Python :: 3.6
Requires-Python: >=2.7
Requires-Dist: backoff (>=1.3.2)
Requires-Dist: influxdb (>=3.0)
Requires-Dist: python-forecastio (>=1.3.5)
Requires-Dist: requests (>=2.0)
Provides-Extra: dev
Requires-Dist: tox; extra == 'dev'
Requires-Dist: yapf; extra == 'dev'
Provides-Extra: doc
Requires-Dist: Sphinx; extra == 'doc'
Requires-Dist: alabaster; extra == 'doc'
Requires-Dist: sphinx-argparse; extra == 'doc'
Requires-Dist: sphinx-autobuild; extra == 'doc'
Provides-Extra: notebook
Requires-Dist: jupyter; extra == 'notebook'
Provides-Extra: test
Requires-Dist: coverage; extra == 'test'
Requires-Dist: mock; extra == 'test'
Requires-Dist: prospector; extra == 'test'
Requires-Dist: responses; extra == 'test'
